{ "sources": [
  { "type": "minecraft:single", "resource": "integrateddynamics:models/drying_basin" },
  { "type": "minecraft:single", "resource": "integrateddynamics:models/squeezer" },
  { "type": "minecraft:single", "resource": "integrateddynamics:item/bucket_menril_resin" },
  { "type": "minecraft:single", "resource": "integrateddynamics:item/bucket_liquid_chorus" },
  { "type": "minecraft:single", "resource": "integrateddynamics:item/portable_logic_programmer" },
  { "type": "minecraft:single", "resource": "integrateddynamics:item/variable" },
  { "type": "minecraft:single", "resource": "integrateddynamics:item/on_the_dynamics_of_integration" },
  { "type": "minecraft:single", "resource": "integrateddynamics:item/variable_transformer_input" },
  { "type": "minecraft:single", "resource": "integrateddynamics:item/menril_berries" },
  { "type": "minecraft:single", "resource": "integrateddynamics:item/labeller" },
  { "type": "minecraft:single", "resource": "integrateddynamics:item/logic_director" },
  { "type": "minecraft:single", "resource": "integrateddynamics:item/crystalized_chorus_chunk" },
  { "type": "minecraft:single", "resource": "integrateddynamics:item/door_menril" },
  { "type": "minecraft:single", "resource": "integrateddynamics:item/wrench" },
  { "type": "minecraft:single", "resource": "integrateddynamics:item/proto_chorus" },
  { "type": "minecraft:single", "resource": "integrateddynamics:item/variable_transformer_output" },
  { "type": "minecraft:single", "resource": "integrateddynamics:item/crystalized_menril_chunk" },
  { "type": "minecraft:single", "resource": "integrateddynamics:valuetype/boolean" },
  { "type": "minecraft:single", "resource": "integrateddynamics:valuetype/integer" },
  { "type": "minecraft:single", "resource": "integrateddynamics:valuetype/number" },
  { "type": "minecraft:single", "resource": "integrateddynamics:valuetype/double" },
  { "type": "minecraft:single", "resource": "integrateddynamics:valuetype/nullable" },
  { "type": "minecraft:single", "resource": "integrateddynamics:valuetype/named" },
  { "type": "minecraft:single", "resource": "integrateddynamics:valuetype/list" },
  { "type": "minecraft:single", "resource": "integrateddynamics:valuetype/operator" },
  { "type": "minecraft:single", "resource": "integrateddynamics:valuetype/object" },
  { "type": "minecraft:single", "resource": "integrateddynamics:valuetype/any" },
  { "type": "minecraft:single", "resource": "integrateddynamics:valuetype/string" },
  { "type": "minecraft:single", "resource": "integrateddynamics:valuetype/nbt" },
  { "type": "minecraft:single", "resource": "integrateddynamics:valuetype/long" },
  { "type": "minecraft:single", "resource": "integrateddynamics:aspect/write/boolean/redstone/pulse" },
  { "type": "minecraft:single", "resource": "integrateddynamics:aspect/write/boolean/redstone" },
  { "type": "minecraft:single", "resource": "integrateddynamics:aspect/write/double/effect/particle" },
  { "type": "minecraft:single", "resource": "integrateddynamics:aspect/write/integer/redstone/pulse" },
  { "type": "minecraft:single", "resource": "integrateddynamics:aspect/write/integer/audio/instrument/didgeridoo" },
  { "type": "minecraft:single", "resource": "integrateddynamics:aspect/write/integer/audio/instrument/bell" },
  { "type": "minecraft:single", "resource": "integrateddynamics:aspect/write/integer/audio/instrument/hat" },
  { "type": "minecraft:single", "resource": "integrateddynamics:aspect/write/integer/audio/instrument/flute" },
  { "type": "minecraft:single", "resource": "integrateddynamics:aspect/write/integer/audio/instrument/basedrum" },
  { "type": "minecraft:single", "resource": "integrateddynamics:aspect/write/integer/audio/instrument/bit" },
  { "type": "minecraft:single", "resource": "integrateddynamics:aspect/write/integer/audio/instrument/iron_xylophone" },
  { "type": "minecraft:single", "resource": "integrateddynamics:aspect/write/integer/audio/instrument/cow_bell" },
  { "type": "minecraft:single", "resource": "integrateddynamics:aspect/write/integer/audio/instrument/bass" },
  { "type": "minecraft:single", "resource": "integrateddynamics:aspect/write/integer/audio/instrument/xylophone" },
  { "type": "minecraft:single", "resource": "integrateddynamics:aspect/write/integer/audio/instrument/chime" },
  { "type": "minecraft:single", "resource": "integrateddynamics:aspect/write/integer/audio/instrument/banjo" },
  { "type": "minecraft:single", "resource": "integrateddynamics:aspect/write/integer/audio/instrument/guitar" },
  { "type": "minecraft:single", "resource": "integrateddynamics:aspect/write/integer/audio/instrument/harp" },
  { "type": "minecraft:single", "resource": "integrateddynamics:aspect/write/integer/audio/instrument/snare" },
  { "type": "minecraft:single", "resource": "integrateddynamics:aspect/write/integer/audio/instrument/pling" },
  { "type": "minecraft:single", "resource": "integrateddynamics:aspect/write/integer/redstone" },
  { "type": "minecraft:single", "resource": "integrateddynamics:aspect/write/string/audio/sound" },
  { "type": "minecraft:single", "resource": "integrateddynamics:aspect/write/string/audio/text" },
  { "type": "minecraft:single", "resource": "integrateddynamics:aspect/read/itemstack/entity/itemframecontents" },
  { "type": "minecraft:single", "resource": "integrateddynamics:aspect/read/nbt/block/tile" },
  { "type": "minecraft:single", "resource": "integrateddynamics:aspect/read/entity/entity" },
  { "type": "minecraft:single", "resource": "integrateddynamics:aspect/read/any/network/value" },
  { "type": "minecraft:single", "resource": "integrateddynamics:aspect/read/block" },
  { "type": "minecraft:single", "resource": "integrateddynamics:aspect/read/long/world/time" },
  { "type": "minecraft:single", "resource": "integrateddynamics:aspect/read/long/world/totaltime" },
  { "type": "minecraft:single", "resource": "integrateddynamics:aspect/read/inventory/itemstack" },
  { "type": "minecraft:single", "resource": "integrateddynamics:aspect/read/list/recipehandler/recipes" },
  { "type": "minecraft:single", "resource": "integrateddynamics:aspect/read/list/entity/players" },
  { "type": "minecraft:single", "resource": "integrateddynamics:aspect/read/list/entity/entities" },
  { "type": "minecraft:single", "resource": "integrateddynamics:aspect/read/list/world/players" },
  { "type": "minecraft:single", "resource": "integrateddynamics:aspect/read/list/fluid/fluidstacks" },
  { "type": "minecraft:single", "resource": "integrateddynamics:aspect/read/list/fluid/capacities" },
  { "type": "minecraft:single", "resource": "integrateddynamics:aspect/read/list/extradimensional/players" },
  { "type": "minecraft:single", "resource": "integrateddynamics:aspect/read/list/inventory/itemstacks" },
  { "type": "minecraft:single", "resource": "integrateddynamics:aspect/read/boolean/recipehandler/applicable" },
  { "type": "minecraft:single", "resource": "integrateddynamics:aspect/read/boolean/fe/applicable" },
  { "type": "minecraft:single", "resource": "integrateddynamics:aspect/read/boolean/fe/canextract" },
  { "type": "minecraft:single", "resource": "integrateddynamics:aspect/read/boolean/fe/isprovider" },
  { "type": "minecraft:single", "resource": "integrateddynamics:aspect/read/boolean/fe/isempty" },
  { "type": "minecraft:single", "resource": "integrateddynamics:aspect/read/boolean/fe/caninsert" },
  { "type": "minecraft:single", "resource": "integrateddynamics:aspect/read/boolean/fe/isfull" },
  { "type": "minecraft:single", "resource": "integrateddynamics:aspect/read/boolean/fe/isnonempty" },
  { "type": "minecraft:single", "resource": "integrateddynamics:aspect/read/boolean/fe/isreceiver" },
  { "type": "minecraft:single", "resource": "integrateddynamics:aspect/read/boolean/network/applicable" },
  { "type": "minecraft:single", "resource": "integrateddynamics:aspect/read/boolean/redstone/nonlow" },
  { "type": "minecraft:single", "resource": "integrateddynamics:aspect/read/boolean/redstone/clock" },
  { "type": "minecraft:single", "resource": "integrateddynamics:aspect/read/boolean/redstone/low" },
  { "type": "minecraft:single", "resource": "integrateddynamics:aspect/read/boolean/redstone/high" },
  { "type": "minecraft:single", "resource": "integrateddynamics:aspect/read/boolean/world/isnight" },
  { "type": "minecraft:single", "resource": "integrateddynamics:aspect/read/boolean/world/isday" },
  { "type": "minecraft:single", "resource": "integrateddynamics:aspect/read/boolean/world/mob" },
  { "type": "minecraft:single", "resource": "integrateddynamics:aspect/read/boolean/world/item" },
  { "type": "minecraft:single", "resource": "integrateddynamics:aspect/read/boolean/world/weather/thunder" },
  { "type": "minecraft:single", "resource": "integrateddynamics:aspect/read/boolean/world/weather/clear" },
  { "type": "minecraft:single", "resource": "integrateddynamics:aspect/read/boolean/world/weather/raining" },
  { "type": "minecraft:single", "resource": "integrateddynamics:aspect/read/boolean/world/entity" },
  { "type": "minecraft:single", "resource": "integrateddynamics:aspect/read/boolean/world/animal" },
  { "type": "minecraft:single", "resource": "integrateddynamics:aspect/read/boolean/world/player" },
  { "type": "minecraft:single", "resource": "integrateddynamics:aspect/read/boolean/fluid/nonempty" },
  { "type": "minecraft:single", "resource": "integrateddynamics:aspect/read/boolean/fluid/applicable" },
  { "type": "minecraft:single", "resource": "integrateddynamics:aspect/read/boolean/fluid/empty" },
  { "type": "minecraft:single", "resource": "integrateddynamics:aspect/read/boolean/fluid/full" },
  { "type": "minecraft:single", "resource": "integrateddynamics:aspect/read/boolean/machine/isworking" },
  { "type": "minecraft:single", "resource": "integrateddynamics:aspect/read/boolean/machine/isworker" },
  { "type": "minecraft:single", "resource": "integrateddynamics:aspect/read/boolean/machine/canwork" },
  { "type": "minecraft:single", "resource": "integrateddynamics:aspect/read/boolean/machine/haswork" },
  { "type": "minecraft:single", "resource": "integrateddynamics:aspect/read/boolean/inventory/nonempty" },
  { "type": "minecraft:single", "resource": "integrateddynamics:aspect/read/boolean/inventory/applicable" },
  { "type": "minecraft:single", "resource": "integrateddynamics:aspect/read/boolean/inventory/empty" },
  { "type": "minecraft:single", "resource": "integrateddynamics:aspect/read/boolean/inventory/full" },
  { "type": "minecraft:single", "resource": "integrateddynamics:aspect/read/boolean/temperature/istemperature" },
  { "type": "minecraft:single", "resource": "integrateddynamics:aspect/read/boolean/block/block" },
  { "type": "minecraft:single", "resource": "integrateddynamics:aspect/read/double/fe/fillratio" },
  { "type": "minecraft:single", "resource": "integrateddynamics:aspect/read/double/world/tps" },
  { "type": "minecraft:single", "resource": "integrateddynamics:aspect/read/double/fluid/fillratio" },
  { "type": "minecraft:single", "resource": "integrateddynamics:aspect/read/double/extradimensional/tps" },
  { "type": "minecraft:single", "resource": "integrateddynamics:aspect/read/double/inventory/fillratio" },
  { "type": "minecraft:single", "resource": "integrateddynamics:aspect/read/double/temperature/defaulttemperature" },
  { "type": "minecraft:single", "resource": "integrateddynamics:aspect/read/double/temperature/temperature" },
  { "type": "minecraft:single", "resource": "integrateddynamics:aspect/read/double/temperature/mintemperature" },
  { "type": "minecraft:single", "resource": "integrateddynamics:aspect/read/double/temperature/maxtemperature" },
  { "type": "minecraft:single", "resource": "integrateddynamics:aspect/read/integer/entity/itemframerotation" },
  { "type": "minecraft:single", "resource": "integrateddynamics:aspect/read/integer/fe/capacity" },
  { "type": "minecraft:single", "resource": "integrateddynamics:aspect/read/integer/fe/amount" },
  { "type": "minecraft:single", "resource": "integrateddynamics:aspect/read/integer/network/energy/stored" },
  { "type": "minecraft:single", "resource": "integrateddynamics:aspect/read/integer/network/energy/consumptionrate" },
  { "type": "minecraft:single", "resource": "integrateddynamics:aspect/read/integer/network/energy/max" },
  { "type": "minecraft:single", "resource": "integrateddynamics:aspect/read/integer/network/energy/batterycount" },
  { "type": "minecraft:single", "resource": "integrateddynamics:aspect/read/integer/network/elementcount" },
  { "type": "minecraft:single", "resource": "integrateddynamics:aspect/read/integer/redstone/value" },
  { "type": "minecraft:single", "resource": "integrateddynamics:aspect/read/integer/redstone/comparator" },
  { "type": "minecraft:single", "resource": "integrateddynamics:aspect/read/integer/world/ticktime" },
  { "type": "minecraft:single", "resource": "integrateddynamics:aspect/read/integer/world/playercount" },
  { "type": "minecraft:single", "resource": "integrateddynamics:aspect/read/integer/world/daytime" },
  { "type": "minecraft:single", "resource": "integrateddynamics:aspect/read/integer/world/lightlevel" },
  { "type": "minecraft:single", "resource": "integrateddynamics:aspect/read/integer/world/raincountdown" },
  { "type": "minecraft:single", "resource": "integrateddynamics:aspect/read/integer/world/entity" },
  { "type": "minecraft:single", "resource": "integrateddynamics:aspect/read/integer/fluid/capacity" },
  { "type": "minecraft:single", "resource": "integrateddynamics:aspect/read/integer/fluid/totalcapacity" },
  { "type": "minecraft:single", "resource": "integrateddynamics:aspect/read/integer/fluid/totalamount" },
  { "type": "minecraft:single", "resource": "integrateddynamics:aspect/read/integer/fluid/tanks" },
  { "type": "minecraft:single", "resource": "integrateddynamics:aspect/read/integer/fluid/amount" },
  { "type": "minecraft:single", "resource": "integrateddynamics:aspect/read/integer/extradimensional/ticktime" },
  { "type": "minecraft:single", "resource": "integrateddynamics:aspect/read/integer/extradimensional/playercount" },
  { "type": "minecraft:single", "resource": "integrateddynamics:aspect/read/integer/extradimensional/random" },
  { "type": "minecraft:single", "resource": "integrateddynamics:aspect/read/integer/audio/instrument/didgeridoo" },
  { "type": "minecraft:single", "resource": "integrateddynamics:aspect/read/integer/audio/instrument/bell" },
  { "type": "minecraft:single", "resource": "integrateddynamics:aspect/read/integer/audio/instrument/hat" },
  { "type": "minecraft:single", "resource": "integrateddynamics:aspect/read/integer/audio/instrument/flute" },
  { "type": "minecraft:single", "resource": "integrateddynamics:aspect/read/integer/audio/instrument/basedrum" },
  { "type": "minecraft:single", "resource": "integrateddynamics:aspect/read/integer/audio/instrument/bit" },
  { "type": "minecraft:single", "resource": "integrateddynamics:aspect/read/integer/audio/instrument/iron_xylophone" },
  { "type": "minecraft:single", "resource": "integrateddynamics:aspect/read/integer/audio/instrument/cow_bell" },
  { "type": "minecraft:single", "resource": "integrateddynamics:aspect/read/integer/audio/instrument/bass" },
  { "type": "minecraft:single", "resource": "integrateddynamics:aspect/read/integer/audio/instrument/xylophone" },
  { "type": "minecraft:single", "resource": "integrateddynamics:aspect/read/integer/audio/instrument/chime" },
  { "type": "minecraft:single", "resource": "integrateddynamics:aspect/read/integer/audio/instrument/banjo" },
  { "type": "minecraft:single", "resource": "integrateddynamics:aspect/read/integer/audio/instrument/guitar" },
  { "type": "minecraft:single", "resource": "integrateddynamics:aspect/read/integer/audio/instrument/harp" },
  { "type": "minecraft:single", "resource": "integrateddynamics:aspect/read/integer/audio/instrument/snare" },
  { "type": "minecraft:single", "resource": "integrateddynamics:aspect/read/integer/audio/instrument/pling" },
  { "type": "minecraft:single", "resource": "integrateddynamics:aspect/read/integer/inventory/slots" },
  { "type": "minecraft:single", "resource": "integrateddynamics:aspect/read/integer/inventory/count" },
  { "type": "minecraft:single", "resource": "integrateddynamics:aspect/read/integer/inventory/slotsfilled" },
  { "type": "minecraft:single", "resource": "integrateddynamics:aspect/read/integer/block/light" },
  { "type": "minecraft:single", "resource": "integrateddynamics:aspect/read/integer/block/posy" },
  { "type": "minecraft:single", "resource": "integrateddynamics:aspect/read/integer/block/posx" },
  { "type": "minecraft:single", "resource": "integrateddynamics:aspect/read/integer/block/posz" },
  { "type": "minecraft:single", "resource": "integrateddynamics:aspect/read/string/world/worldname" },
  { "type": "minecraft:single", "resource": "integrateddynamics:aspect/read/string/block/biome" },
  { "type": "minecraft:single", "resource": "integrateddynamics:aspect/read/string/block/dimension" },
  { "type": "minecraft:single", "resource": "integrateddynamics:aspect/read/operator/recipehandler/recipeoutputsingle" },
  { "type": "minecraft:single", "resource": "integrateddynamics:aspect/read/operator/recipehandler/recipeinputsingle" },
  { "type": "minecraft:single", "resource": "integrateddynamics:aspect/read/operator/recipehandler/recipeoutputlist" },
  { "type": "minecraft:single", "resource": "integrateddynamics:aspect/read/operator/recipehandler/recipeinput" },
  { "type": "minecraft:single", "resource": "integrateddynamics:aspect/read/operator/recipehandler/recipeoutput" },
  { "type": "minecraft:single", "resource": "integrateddynamics:aspect/read/operator/recipehandler/recipeinputlist" },
  { "type": "minecraft:single", "resource": "integrateddynamics:aspect/read/fluidstack/block" },
  { "type": "minecraft:single", "resource": "integrateddynamics:aspect/read/fluidstack/fluid" },
  { "type": "minecraft:single", "resource": "integrateddynamics:part/part_connector_mono_directional_back_inactive" },
  { "type": "minecraft:single", "resource": "integrateddynamics:part/part_connector_omni_directional_front_inactive" },
  { "type": "minecraft:single", "resource": "integrateddynamics:part/machine_writer_front_error" },
  { "type": "minecraft:single", "resource": "integrateddynamics:part/part_connector_omni_directional_back_inactive" },
  { "type": "minecraft:single", "resource": "integrateddynamics:part/entity_writer_front_active" },
  { "type": "minecraft:single", "resource": "integrateddynamics:part/empty_writer_front" },
  { "type": "minecraft:single", "resource": "integrateddynamics:part/machine_reader_front" },
  { "type": "minecraft:single", "resource": "integrateddynamics:part/redstone_writer_front_active" },
  { "type": "minecraft:single", "resource": "integrateddynamics:part/empty_reader_back" },
  { "type": "minecraft:single", "resource": "integrateddynamics:part/part_connector_omni_directional_front" },
  { "type": "minecraft:single", "resource": "integrateddynamics:part/fluid_reader_front" },
  { "type": "minecraft:single", "resource": "integrateddynamics:part/block_reader_back" },
  { "type": "minecraft:single", "resource": "integrateddynamics:part/audio_writer_front_inactive" },
  { "type": "minecraft:single", "resource": "integrateddynamics:part/extradimensional_reader_front" },
  { "type": "minecraft:single", "resource": "integrateddynamics:part/entity_writer_front_error" },
  { "type": "minecraft:single", "resource": "integrateddynamics:part/audio_writer_front_error" },
  { "type": "minecraft:single", "resource": "integrateddynamics:part/panel_back_error" },
  { "type": "minecraft:single", "resource": "integrateddynamics:part/part_connector_mono_directional_front" },
  { "type": "minecraft:single", "resource": "integrateddynamics:part/inventory_reader_front" },
  { "type": "minecraft:single", "resource": "integrateddynamics:part/redstone_writer_front_inactive" },
  { "type": "minecraft:single", "resource": "integrateddynamics:part/effect_writer_front_inactive" },
  { "type": "minecraft:single", "resource": "integrateddynamics:part/fluid_reader_back" },
  { "type": "minecraft:single", "resource": "integrateddynamics:part/entity_reader_back" },
  { "type": "minecraft:single", "resource": "integrateddynamics:part/audio_reader_back" },
  { "type": "minecraft:single", "resource": "integrateddynamics:part/redstone_reader_front" },
  { "type": "minecraft:single", "resource": "integrateddynamics:part/empty_reader_front" },
  { "type": "minecraft:single", "resource": "integrateddynamics:part/world_reader_back" },
  { "type": "minecraft:single", "resource": "integrateddynamics:part/panel_front_dark" },
  { "type": "minecraft:single", "resource": "integrateddynamics:part/inventory_reader_back" },
  { "type": "minecraft:single", "resource": "integrateddynamics:part/redstone_writer_front_error" },
  { "type": "minecraft:single", "resource": "integrateddynamics:part/part_connector_omni_directional_back" },
  { "type": "minecraft:single", "resource": "integrateddynamics:part/effect_reader_back" },
  { "type": "minecraft:single", "resource": "integrateddynamics:part/world_reader_front" },
  { "type": "minecraft:single", "resource": "integrateddynamics:part/machine_reader_back" },
  { "type": "minecraft:single", "resource": "integrateddynamics:part/inventory_writer_front_inactive" },
  { "type": "minecraft:single", "resource": "integrateddynamics:part/network_reader_front" },
  { "type": "minecraft:single", "resource": "integrateddynamics:part/effect_writer_front_active" },
  { "type": "minecraft:single", "resource": "integrateddynamics:part/extradimensional_reader_back" },
  { "type": "minecraft:single", "resource": "integrateddynamics:part/machine_writer_front_inactive" },
  { "type": "minecraft:single", "resource": "integrateddynamics:part/effect_writer_front_error" },
  { "type": "minecraft:single", "resource": "integrateddynamics:part/audio_writer_front_active" },
  { "type": "minecraft:single", "resource": "integrateddynamics:part/audio_reader_front" },
  { "type": "minecraft:single", "resource": "integrateddynamics:part/panel_back_active" },
  { "type": "minecraft:single", "resource": "integrateddynamics:part/entity_reader_front" },
  { "type": "minecraft:single", "resource": "integrateddynamics:part/network_reader_back" },
  { "type": "minecraft:single", "resource": "integrateddynamics:part/redstone_reader_back" },
  { "type": "minecraft:single", "resource": "integrateddynamics:part/panel_back_inactive" },
  { "type": "minecraft:single", "resource": "integrateddynamics:part/effect_reader_front" },
  { "type": "minecraft:single", "resource": "integrateddynamics:part/block_reader_front" },
  { "type": "minecraft:single", "resource": "integrateddynamics:part/inventory_writer_front_active" },
  { "type": "minecraft:single", "resource": "integrateddynamics:part/machine_writer_front_active" },
  { "type": "minecraft:single", "resource": "integrateddynamics:part/part_connector_mono_directional_back" },
  { "type": "minecraft:single", "resource": "integrateddynamics:part/part_connector_mono_directional_front_inactive" },
  { "type": "minecraft:single", "resource": "integrateddynamics:part/entity_writer_front_inactive" },
  { "type": "minecraft:single", "resource": "integrateddynamics:part/inventory_writer_front_error" },
  { "type": "minecraft:single", "resource": "integrateddynamics:part/panel_front_light" },
  { "type": "minecraft:single", "resource": "integrateddynamics:customoverlay/delay" },
  { "type": "minecraft:single", "resource": "integrateddynamics:customoverlay/proxy" },
  { "type": "minecraft:single", "resource": "integrateddynamics:slot/variable_empty" },
  { "type": "minecraft:single", "resource": "integrateddynamics:block/logic_programmer_top" },
  { "type": "minecraft:single", "resource": "integrateddynamics:block/menril_leaves_fancy" },
  { "type": "minecraft:single", "resource": "integrateddynamics:block/variablestore_top" },
  { "type": "minecraft:single", "resource": "integrateddynamics:block/coal_generator_side" },
  { "type": "minecraft:single", "resource": "integrateddynamics:block/door_menril_lower" },
  { "type": "minecraft:single", "resource": "integrateddynamics:block/mechanical_drying_basin_off" },
  { "type": "minecraft:single", "resource": "integrateddynamics:block/variablestore_side" },
  { "type": "minecraft:single", "resource": "integrateddynamics:block/menril_log_top" },
  { "type": "minecraft:single", "resource": "integrateddynamics:block/mechanical_drying_basin_on" },
  { "type": "minecraft:single", "resource": "integrateddynamics:block/energy_battery_side_full" },
  { "type": "minecraft:single", "resource": "integrateddynamics:block/menril_leaves_fast" },
  { "type": "minecraft:single", "resource": "integrateddynamics:block/menril_log_stripped" },
  { "type": "minecraft:single", "resource": "integrateddynamics:block/menril_log_filled" },
  { "type": "minecraft:single", "resource": "integrateddynamics:block/menril_resin_flow" },
  { "type": "minecraft:single", "resource": "integrateddynamics:block/door_menril_upper" },
  { "type": "minecraft:single", "resource": "integrateddynamics:block/menril_torch" },
  { "type": "minecraft:single", "resource": "integrateddynamics:block/liquid_chorus_flow" },
  { "type": "minecraft:single", "resource": "integrateddynamics:block/mechanical_squeezer_x_off" },
  { "type": "minecraft:single", "resource": "integrateddynamics:block/proxy_back" },
  { "type": "minecraft:single", "resource": "integrateddynamics:block/energy_battery_side_creative" },
  { "type": "minecraft:single", "resource": "integrateddynamics:block/variablestore_front" },
  { "type": "minecraft:single", "resource": "integrateddynamics:block/menril_sapling" },
  { "type": "minecraft:single", "resource": "integrateddynamics:block/energy_battery_up" },
  { "type": "minecraft:single", "resource": "integrateddynamics:block/proxy_top" },
  { "type": "minecraft:single", "resource": "integrateddynamics:block/coal_generator_front_on" },
  { "type": "minecraft:single", "resource": "integrateddynamics:block/cable" },
  { "type": "minecraft:single", "resource": "integrateddynamics:block/mechanical_squeezer_x_on" },
  { "type": "minecraft:single", "resource": "integrateddynamics:block/energy_battery_side" },
  { "type": "minecraft:single", "resource": "integrateddynamics:block/proxy_front" },
  { "type": "minecraft:single", "resource": "integrateddynamics:block/menril_planks" },
  { "type": "minecraft:single", "resource": "integrateddynamics:block/crystalized_menril_brick" },
  { "type": "minecraft:single", "resource": "integrateddynamics:block/logic_programmer_side" },
  { "type": "minecraft:single", "resource": "integrateddynamics:block/menril_resin_still" },
  { "type": "minecraft:single", "resource": "integrateddynamics:block/crystalized_chorus_block" },
  { "type": "minecraft:single", "resource": "integrateddynamics:block/delay_side" },
  { "type": "minecraft:single", "resource": "integrateddynamics:block/menril_log" },
  { "type": "minecraft:single", "resource": "integrateddynamics:block/delay_top" },
  { "type": "minecraft:single", "resource": "integrateddynamics:block/liquid_chorus_still" },
  { "type": "minecraft:single", "resource": "integrateddynamics:block/crystalized_menril_block" },
  { "type": "minecraft:single", "resource": "integrateddynamics:block/menril_torch_stone" },
  { "type": "minecraft:single", "resource": "integrateddynamics:block/mechanical_squeezer_y" },
  { "type": "minecraft:single", "resource": "integrateddynamics:block/menril_log_top_stripped" },
  { "type": "minecraft:single", "resource": "integrateddynamics:block/crystalized_chorus_brick" },
  { "type": "minecraft:single", "resource": "integrateddynamics:block/materializer_front" },
  { "type": "minecraft:single", "resource": "integrateddynamics:block/coal_generator_front_off" },
  { "type": "minecraft:single", "resource": "integrateddynamics:block/delay_front" },
  { "type": "minecraft:single", "resource": "integrateddynamics:block/energy_battery_overlay" },
  { "type": "minecraft:single", "resource": "integrateddynamics:block/proxy_side" },
  { "type": "minecraft:single", "resource": "integrateddynamics:block/facade" }
]}
